<?xml version="1.0" encoding="UTF-8"?>
<comment version="3.0">
  <caption>Car crash, be hollow on the body car , vibrant color light</caption>
  <note/>
  <place/>
  <categories>
    <category value="accident"/>
    <category value="auto"/>
    <category value="automobile"/>
    <category value="bender"/>
    <category value="broken"/>
    <category value="bumper"/>
    <category value="car"/>
    <category value="collision"/>
    <category value="crush"/>
    <category value="damage"/>
    <category value="dancer"/>
    <category value="dangerous"/>
    <category value="death"/>
    <category value="dent"/>
    <category value="drive"/>
    <category value="emergency"/>
    <category value="headlight"/>
    <category value="highway"/>
    <category value="hood"/>
    <category value="injury"/>
    <category value="metal"/>
    <category value="problem"/>
    <category value="repair"/>
    <category value="road"/>
    <category value="safe"/>
    <category value="safety"/>
    <category value="smash"/>
    <category value="speed"/>
    <category value="street"/>
    <category value="traffic"/>
    <category value="transportation"/>
    <category value="vehicle"/>
    <category value="wreck"/>
    <category value="back"/>
    <category value="dust"/>
    <category value="accident"/>
    <category value="auto"/>
    <category value="automobile"/>
    <category value="bender"/>
    <category value="broken"/>
    <category value="bumper"/>
    <category value="car"/>
    <category value="collision"/>
    <category value="crush"/>
    <category value="damage"/>
    <category value="dancer"/>
    <category value="dangerous"/>
    <category value="death"/>
    <category value="dent"/>
    <category value="drive"/>
    <category value="emergency"/>
    <category value="headlight"/>
    <category value="highway"/>
    <category value="hood"/>
    <category value="injury"/>
    <category value="metal"/>
    <category value="problem"/>
    <category value="repair"/>
    <category value="road"/>
    <category value="safe"/>
    <category value="safety"/>
    <category value="smash"/>
    <category value="speed"/>
    <category value="street"/>
    <category value="traffic"/>
    <category value="transportation"/>
    <category value="vehicle"/>
    <category value="wreck"/>
    <category value="back"/>
    <category value="dust"/>
  </categories>
</comment>
